{"requiredParameters":["InputFile"],"description":"Minimum Python2 container with pip","icon":"/data/python2.png","ports":null,"docker_image_name":"biodepot/python2","outputs":{"py/reduce":[{"py/type":"collections.OrderedDict"},{"py/tuple":[]},null,null,{"py/tuple":[{"py/tuple":["OutputDir",{"type":{"py/type":"__builtin__.str"},"default":null}]}]}]},"priority":"11","command":["python "],"inputs":{"py/reduce":[{"py/type":"collections.OrderedDict"},{"py/tuple":[]},null,null,{"py/tuple":[{"py/tuple":["inputFile",{"callback":null,"type":{"py/type":"__builtin__.str"}}]},{"py/tuple":["Trigger",{"type":{"py/type":"__builtin__.str"},"callback":null}]}]}]},"name":"Python2","docker_image_tag":"2.7.15__alpine-3.7__b6c52c1c__ce08e7c9__0da9cd30","persistentSettings":"all","volumes":null,"autoMap":true,"parameters":{"py/reduce":[{"py/type":"collections.OrderedDict"},{"py/tuple":[]},null,null,{"py/tuple":[{"py/tuple":["InputFile",{"argument":true,"label":"Script","type":"file","flag":null}]}]}]}}