{"priority":"103","volumes":null,"command":["jupyter _bwb{subcommand} _bwb{startingNotebook}"],"outputs":{"py/reduce":[{"py/type":"collections.OrderedDict"},{"py/tuple":[]},null,null,{"py/tuple":[{"py/tuple":["OutputDir",{"type":{"py/type":"builtins.str"},"default":null}]},{"py/tuple":["outputNotebook",{"type":{"py/type":"builtins.str"},"default":null}]}]}]},"runDockerMap":null,"ports":null,"icon":null,"requiredParameters":["subcommand","ip","port"],"name":"jupyter_bioc","autoMap":true,"description":"Base installation of Jupyter","docker_image_name":"biodepot/jupyter","docker_image_tag":"6.5.2__bioc-r_3.16-ubuntu-22.04-r-4.2.2__dcf4705a__35f295e6__ee7d8c88","persistentSettings":"all","inputs":{"py/reduce":[{"py/type":"collections.OrderedDict"},{"py/tuple":[]},null,null,{"py/tuple":[{"py/tuple":["InputDir",{"callback":null,"type":{"py/type":"builtins.str"}}]},{"py/tuple":["Trigger",{"type":{"py/type":"builtins.str"},"callback":null}]},{"py/tuple":["startingNotebook",{"type":{"py/type":"builtins.str"},"callback":null}]}]}]},"parameters":{"py/reduce":[{"py/type":"collections.OrderedDict"},{"py/tuple":[]},null,null,{"py/tuple":[{"py/tuple":["subcommand",{"flag":"","default":"notebook","label":"Subcommand","type":"str"}]},{"py/tuple":["startingNotebook",{"type":"file","argument":true,"label":"Notebook file","flag":null}]},{"py/tuple":["type",{"flag":"--to ","label":"(nbconvert) to type","default":"notebook","type":"str"}]},{"py/tuple":["outputNotebook",{"flag":"--output ","label":"(nbconvert) Output notebook","type":"file"}]},{"py/tuple":["debug",{"type":"bool","label":"Debug:","flag":"--debug"}]},{"py/tuple":["generateConfig",{"type":"bool","label":"Generate-config:","flag":"--generate-config"}]},{"py/tuple":["autoyes",{"default":true,"label":"No prompts","type":"bool","flag":"-y"}]},{"py/tuple":["allowRoot",{"flag":"--allow-root","type":"bool","default":true,"label":"Allow root:"}]},{"py/tuple":["loglevel",{"flag":"--log-level","label":"Log Level","default":"30","type":"str"}]},{"py/tuple":["ip",{"type":"str","default":"0.0.0.0","label":"IP:","flag":"--ip="}]},{"py/tuple":["port",{"type":"int","default":8888,"label":"Port:","flag":"--port="}]},{"py/tuple":["config",{"type":"file","label":"Config file:","flag":"--config="}]},{"py/tuple":["transport",{"type":"str","label":"Transport","flag":"--transport="}]},{"py/tuple":["keyfile",{"label":"Key file:","type":"file","flag":"--keyfile="}]},{"py/tuple":["certfile",{"flag":"--certfile=","type":"file","label":"Cert file:"}]},{"py/tuple":["clientca",{"type":"file","label":"Client cert authority","flag":"--client-ca="}]},{"py/tuple":["nomathjax",{"type":"bool","label":"Disable mathjax:","flag":"--no-mathjax"}]},{"py/tuple":["browser",{"flag":"--browser=","label":"Custom browser:","type":"str"}]}]}]}}